LinearRegression/__init__.py
LinearRegression-0.0.1.dist-info/LICENSE.txt
LinearRegression-0.0.1.dist-info/METADATA
LinearRegression-0.0.1.dist-info/WHEEL
LinearRegression-0.0.1.dist-info/top_level.txt
LinearRegression-0.0.1.dist-info/RECORD
