Metadata-Version: 2.1
Name: LinearRegression
Version: 0.0.1
Summary: Linear Regression From Scratch
Home-page: UNKNOWN
Author: Karthi Prasad
Author-email: Teamoctaholix@gmail.com
License: MIT
Platform: UNKNOWN
License-File: LICENSE.txt
